cirque_pinnacle.cpython-37m-aarch64-linux-gnu.so
cirque_pinnacle-stubs/__init__.pyi
cirque_pinnacle-1.0.1.dist-info/LICENSE
cirque_pinnacle-1.0.1.dist-info/WHEEL
cirque_pinnacle-1.0.1.dist-info/top_level.txt
cirque_pinnacle-1.0.1.dist-info/RECORD
cirque_pinnacle-1.0.1.dist-info/METADATA
