Metadata-Version: 2.1
Name: cirque-pinnacle
Version: 1.0.1
Summary: A python package for the wrapping CirquePinnacle C++ library.
Author-email: Brendan Doherty <2bndy5@gmail.com>
License: MIT
Project-URL: Documentation, https://cirquepinnacle.rtfd.io/
Project-URL: Source, https://github.com/2bndy5/CirquePinnacle
Project-URL: Tracker, https://github.com/2bndy5/CirquePinnacle/issues
Keywords: cirque,pinnacle,raspberry,pi,linux,driver,touch,sensor
Classifier: Development Status :: 3 - Alpha
Classifier: Intended Audience :: Developers
Classifier: License :: OSI Approved :: MIT License
Classifier: Operating System :: POSIX :: Linux
Classifier: Programming Language :: C++
Classifier: Programming Language :: Python :: 3
Classifier: Programming Language :: Python :: 3.7
Classifier: Programming Language :: Python :: 3.8
Classifier: Programming Language :: Python :: 3.9
Classifier: Programming Language :: Python :: 3.10
Classifier: Topic :: Software Development :: Libraries
Classifier: Topic :: System :: Hardware
Classifier: Topic :: System :: Hardware :: Hardware Drivers
Classifier: Typing :: Typed
Requires-Python: >=3.7
License-File: LICENSE
